CA21062UNO/__init__.py
CA21062UNO/metodos_numericos.py
ca21062uno-1.1.0.dist-info/licenses/LICENSE
ca21062uno-1.1.0.dist-info/METADATA
ca21062uno-1.1.0.dist-info/WHEEL
ca21062uno-1.1.0.dist-info/top_level.txt
ca21062uno-1.1.0.dist-info/RECORD
